blockmatching/__init__.py
blockmatching/background.py
blockmatching/blockmatching.py
blockmatching/clustering.py
blockmatching/dlayers.py
blockmatching/forecast.py
blockmatching/motionlayers.py
blockmatching/savevideo.py
blockmatching/vectormask.py
test/__init__.py
test/test_layers.py
blockmatching-1.2.1.dist-info/METADATA
blockmatching-1.2.1.dist-info/WHEEL
blockmatching-1.2.1.dist-info/top_level.txt
blockmatching-1.2.1.dist-info/RECORD
