Metadata-Version: 2.1
Name: blockmatching
Version: 1.2.1
Summary: Block Matching Algorithm
Home-page: https://github.com/duducosmos/blockmatching
Author: Eduardo S. Pereira
Author-email: pereira.somoza@gmail.com
License: Apache License 2.0
Platform: UNKNOWN
Requires-Dist: Pillow
Requires-Dist: networkx
Requires-Dist: numba
Requires-Dist: numpy
Requires-Dist: opencv-python
Requires-Dist: scipy
Requires-Dist: sk-video
